ByHelpers/__init__.py
ByHelpers/applogger.py
ByHelpers/attributes.py
ByHelpers/functions.py
ByHelpers/nutrition_facts.py
ByHelpers/rabbit_engine.py
ByHelpers-0.1.4.dist-info/LICENSE.txt
ByHelpers-0.1.4.dist-info/METADATA
ByHelpers-0.1.4.dist-info/WHEEL
ByHelpers-0.1.4.dist-info/top_level.txt
ByHelpers-0.1.4.dist-info/RECORD
