Metadata-Version: 2.1
Name: ByHelpers
Version: 0.1.4
Summary: Library used by ByPrice scrapers
Home-page: https://github.com/ByPrice/ByHelpers
Author: Kevin B. Garcia Alonso
Author-email: kevangy@hotmail.com
License: UNKNOWN
Download-URL: https://github.com/ByPrice/ByHelpers/tarball/0.1.3
Keywords: ByPrice
Platform: UNKNOWN
Classifier: Programming Language :: Python :: 3
Classifier: License :: OSI Approved :: MIT License
Requires-Dist: pika (==0.10.0)
Requires-Dist: fuzzywuzzy (==0.16.0)
Requires-Dist: google-cloud-logging (==1.10.0)
